pixivd/AESCipher.py
pixivd/api.py
pixivd/i18n.py
pixivd/model.py
pixivd/pixivd.py
pixivd/locale/en_US/LC_MESSAGES/messages.mo
pixivd/locale/en_US/LC_MESSAGES/messages.po
pixivd/locale/zh_CN/LC_MESSAGES/messages.mo
pixivd/locale/zh_CN/LC_MESSAGES/messages.po
pixivd-3.1.1.dist-info/licenses/LICENSE
pixivd-3.1.1.dist-info/METADATA
pixivd-3.1.1.dist-info/WHEEL
pixivd-3.1.1.dist-info/entry_points.txt
pixivd-3.1.1.dist-info/top_level.txt
pixivd-3.1.1.dist-info/RECORD
