Metadata-Version: 2.4
Name: pixivd
Version: 3.1.1
Summary: A simple tool to download illustrations from Pixiv.
Author-email: KK <bebound@gmail.com>
License-Expression: MIT
Project-URL: homepage, https://github.com/bebound/pixiv
Project-URL: Source, https://github.com/bebound/pixiv
Classifier: Programming Language :: Python :: 3
Classifier: Operating System :: OS Independent
Requires-Python: >=3.9
License-File: LICENSE
Requires-Dist: requests>=2.4.3
Requires-Dist: pyaes>=1.6.1
Requires-Dist: docopt>=0.6.2
Requires-Dist: tqdm
Requires-Dist: PixivPy>=3.6.0
Dynamic: license-file
